{"schemaVersion":1,"logo":{"imageUrl":"logo.png","alt":"Crypto.com - One-click Farming on Crypto.com Exchange. Deposit CRO and earn Zilliqa (ZIL) over 30 days! Visit crypto.com/exchange now","companyName":"Crypto.com","destinationUrl":"https://auth.crypto.com/exchange/signup?utm_source=Brave&utm_medium=Sponsored%20Image&utm_campaign=Brave%3AWW-en%3ASponsored-Image_SuperchargerNEAR&utm_content=Sponsored-Image_SuperchargerNEAR"},"wallpapers":[{"imageUrl":"background-1.jpg","focalPoint":{"x":1112,"y":720},"creativeInstanceId":"46618adb-8649-40cf-85e7-c5ac899c3e8b"},{"imageUrl":"background-3.jpg","focalPoint":{"x":1297,"y":720},"creativeInstanceId":"5f4907ef-dc38-4146-93da-cff3e3c20d66"},{"imageUrl":"background-2.jpg","focalPoint":{"x":903,"y":720},"creativeInstanceId":"763f2fd1-86cc-4f73-9a95-b43b0d49d39d"}]}